{
    "id": "bq:nv:6",
    "counties": [
        {
            "id": "32510",
            "results": [
                {
                    "id": "1",
                    "votes": 590
                },
                {
                    "id": "2",
                    "votes": 357
                }
            ],
            "progress": {
                "mode": "eevp",
                "pct": 0.52
            }
        },
        {
            "id": "32029",
            "results": [
                {
                    "id": "1",
                    "votes": 618
                },
                {
                    "id": "2",
                    "votes": 787
                }
            ],
            "progress": {
                "mode": "eevp",
                "pct": 0.71
            }
        },
        {
            "id": "32017",
            "results": [
                {
                    "id": "1",
                    "votes": 324
                },
                {
                    "id": "2",
                    "votes": 354
                }
            ],
            "progress": {
                "mode": "eevp",
                "pct": 0.93
            }
        },
        {
            "id": "32027",
            "results": [
                {
                    "id": "1",
                    "votes": 312
                },
                {
                    "id": "2",
                    "votes": 766
                }
            ],
            "progress": {
                "mode": "eevp",
                "pct": 0.42
            }
        },
        {
            "id": "32011",
            "results": [
                {
                    "id": "1",
                    "votes": 366
                },
                {
                    "id": "2",
                    "votes": 178
                }
            ],
            "progress": {
                "mode": "eevp",
                "pct": 0.0
            }
        },
        {
            "id": "32021",
            "results": [
                {
                    "id": "1",
                    "votes": 610
                },
                {
                    "id": "2",
                    "votes": 197
                }
            ],
            "progress": {
                "mode": "eevp",
                "pct": 0.98
            }
        },
        {
            "id": "32033",
            "results": [
                {
                    "id": "1",
                    "votes": 476
                },
                {
                    "id": "2",
                    "votes": 595
                }
            ],
            "progress": {
                "mode": "eevp",
                "pct": 0.64
            }
        },
        {
            "id": "32003",
            "results": [
                {
                    "id": "1",
                    "votes": 308
                },
                {
                    "id": "2",
                    "votes": 221
                }
            ],
            "progress": {
                "mode": "eevp",
                "pct": 0.99
            }
        },
        {
            "id": "32023",
            "results": [
                {
                    "id": "1",
                    "votes": 816
                },
                {
                    "id": "2",
                    "votes": 794
                }
            ],
            "progress": {
                "mode": "eevp",
                "pct": 0.11
            }
        },
        {
            "id": "32009",
            "results": [
                {
                    "id": "1",
                    "votes": 255
                },
                {
                    "id": "2",
                    "votes": 142
                }
            ],
            "progress": {
                "mode": "eevp",
                "pct": 0.04
            }
        },
        {
            "id": "32005",
            "results": [
                {
                    "id": "1",
                    "votes": 406
                },
                {
                    "id": "2",
                    "votes": 227
                }
            ],
            "progress": {
                "mode": "eevp",
                "pct": 0.69
            }
        },
        {
            "id": "32007",
            "results": [
                {
                    "id": "1",
                    "votes": 616
                },
                {
                    "id": "2",
                    "votes": 333
                }
            ],
            "progress": {
                "mode": "eevp",
                "pct": 0.78
            }
        },
        {
            "id": "32013",
            "results": [
                {
                    "id": "1",
                    "votes": 706
                },
                {
                    "id": "2",
                    "votes": 959
                }
            ],
            "progress": {
                "mode": "eevp",
                "pct": 0.64
            }
        },
        {
            "id": "32019",
            "results": [
                {
                    "id": "1",
                    "votes": 628
                },
                {
                    "id": "2",
                    "votes": 385
                }
            ],
            "progress": {
                "mode": "eevp",
                "pct": 0.72
            }
        },
        {
            "id": "32001",
            "results": [
                {
                    "id": "1",
                    "votes": 452
                },
                {
                    "id": "2",
                    "votes": 122
                }
            ],
            "progress": {
                "mode": "eevp",
                "pct": 0.72
            }
        },
        {
            "id": "32015",
            "results": [
                {
                    "id": "1",
                    "votes": 973
                },
                {
                    "id": "2",
                    "votes": 260
                }
            ],
            "progress": {
                "mode": "eevp",
                "pct": 0.18
            }
        },
        {
            "id": "32031",
            "results": [
                {
                    "id": "1",
                    "votes": 579
                },
                {
                    "id": "2",
                    "votes": 377
                }
            ],
            "progress": {
                "mode": "eevp",
                "pct": 0.14
            }
        }
    ]
}