{
    "eventId": "2024-11-05",
    "id": "ap:51:47806",
    "resultsType": "live",
    "timestamp": "2024-09-25T14:33:16.204000Z",
    "counties": [
        {
            "id": "51001",
            "results": [
                {
                    "id": "51423",
                    "votes": 61099
                },
                {
                    "id": "71716",
                    "votes": 87399
                }
            ],
            "progress": {
                "mode": "eevp",
                "pct": 0.65
            }
        },
        {
            "id": "51003",
            "results": [
                {
                    "id": "51423",
                    "votes": 53651
                },
                {
                    "id": "71716",
                    "votes": 22457
                }
            ],
            "progress": {
                "mode": "eevp",
                "pct": 0.52
            }
        },
        {
            "id": "51005",
            "results": [
                {
                    "id": "51423",
                    "votes": 82302
                },
                {
                    "id": "71716",
                    "votes": 63268
                }
            ],
            "progress": {
                "mode": "eevp",
                "pct": 0.59
            }
        },
        {
            "id": "51007",
            "results": [
                {
                    "id": "51423",
                    "votes": 52069
                },
                {
                    "id": "71716",
                    "votes": 92287
                }
            ],
            "progress": {
                "mode": "eevp",
                "pct": 0.01
            }
        },
        {
            "id": "51009",
            "results": [
                {
                    "id": "51423",
                    "votes": 45222
                },
                {
                    "id": "71716",
                    "votes": 84089
                }
            ],
            "progress": {
                "mode": "eevp",
                "pct": 0.49
            }
        },
        {
            "id": "51011",
            "results": [
                {
                    "id": "51423",
                    "votes": 73403
                },
                {
                    "id": "71716",
                    "votes": 61255
                }
            ],
            "progress": {
                "mode": "eevp",
                "pct": 0.25
            }
        },
        {
            "id": "51013",
            "results": [
                {
                    "id": "51423",
                    "votes": 51442
                },
                {
                    "id": "71716",
                    "votes": 49225
                }
            ],
            "progress": {
                "mode": "eevp",
                "pct": 0.09
            }
        },
        {
            "id": "51015",
            "results": [
                {
                    "id": "51423",
                    "votes": 47173
                },
                {
                    "id": "71716",
                    "votes": 39692
                }
            ],
            "progress": {
                "mode": "eevp",
                "pct": 0.59
            }
        },
        {
            "id": "51017",
            "results": [
                {
                    "id": "51423",
                    "votes": 59890
                },
                {
                    "id": "71716",
                    "votes": 37027
                }
            ],
            "progress": {
                "mode": "eevp",
                "pct": 0.08
            }
        },
        {
            "id": "51019",
            "results": [
                {
                    "id": "51423",
                    "votes": 69872
                },
                {
                    "id": "71716",
                    "votes": 60805
                }
            ],
            "progress": {
                "mode": "eevp",
                "pct": 0.88
            }
        },
        {
            "id": "51021",
            "results": [
                {
                    "id": "51423",
                    "votes": 78053
                },
                {
                    "id": "71716",
                    "votes": 40986
                }
            ],
            "progress": {
                "mode": "eevp",
                "pct": 0.99
            }
        },
        {
            "id": "51023",
            "results": [
                {
                    "id": "51423",
                    "votes": 84171
                },
                {
                    "id": "71716",
                    "votes": 30751
                }
            ],
            "progress": {
                "mode": "eevp",
                "pct": 0.0
            }
        },
        {
            "id": "51025",
            "results": [
                {
                    "id": "51423",
                    "votes": 25831
                },
                {
                    "id": "71716",
                    "votes": 25420
                }
            ],
            "progress": {
                "mode": "eevp",
                "pct": 0.42
            }
        },
        {
            "id": "51027",
            "results": [
                {
                    "id": "51423",
                    "votes": 11063
                },
                {
                    "id": "71716",
                    "votes": 14676
                }
            ],
            "progress": {
                "mode": "eevp",
                "pct": 0.41
            }
        },
        {
            "id": "51029",
            "results": [
                {
                    "id": "51423",
                    "votes": 83785
                },
                {
                    "id": "71716",
                    "votes": 42510
                }
            ],
            "progress": {
                "mode": "eevp",
                "pct": 0.99
            }
        },
        {
            "id": "51031",
            "results": [
                {
                    "id": "51423",
                    "votes": 19258
                },
                {
                    "id": "71716",
                    "votes": 61633
                }
            ],
            "progress": {
                "mode": "eevp",
                "pct": 0.84
            }
        },
        {
            "id": "51033",
            "results": [
                {
                    "id": "51423",
                    "votes": 75015
                },
                {
                    "id": "71716",
                    "votes": 11194
                }
            ],
            "progress": {
                "mode": "eevp",
                "pct": 0.77
            }
        },
        {
            "id": "51035",
            "results": [
                {
                    "id": "51423",
                    "votes": 61832
                },
                {
                    "id": "71716",
                    "votes": 23002
                }
            ],
            "progress": {
                "mode": "eevp",
                "pct": 0.57
            }
        },
        {
            "id": "51036",
            "results": [
                {
                    "id": "51423",
                    "votes": 42080
                },
                {
                    "id": "71716",
                    "votes": 47050
                }
            ],
            "progress": {
                "mode": "eevp",
                "pct": 0.06
            }
        },
        {
            "id": "51037",
            "results": [
                {
                    "id": "51423",
                    "votes": 33981
                },
                {
                    "id": "71716",
                    "votes": 65361
                }
            ],
            "progress": {
                "mode": "eevp",
                "pct": 0.47
            }
        },
        {
            "id": "51041",
            "results": [
                {
                    "id": "51423",
                    "votes": 29431
                },
                {
                    "id": "71716",
                    "votes": 80060
                }
            ],
            "progress": {
                "mode": "eevp",
                "pct": 0.86
            }
        },
        {
            "id": "51043",
            "results": [
                {
                    "id": "51423",
                    "votes": 52039
                },
                {
                    "id": "71716",
                    "votes": 45658
                }
            ],
            "progress": {
                "mode": "eevp",
                "pct": 0.67
            }
        },
        {
            "id": "51045",
            "results": [
                {
                    "id": "51423",
                    "votes": 81259
                },
                {
                    "id": "71716",
                    "votes": 99756
                }
            ],
            "progress": {
                "mode": "eevp",
                "pct": 0.14
            }
        },
        {
            "id": "51047",
            "results": [
                {
                    "id": "51423",
                    "votes": 21970
                },
                {
                    "id": "71716",
                    "votes": 77341
                }
            ],
            "progress": {
                "mode": "eevp",
                "pct": 0.53
            }
        },
        {
            "id": "51049",
            "results": [
                {
                    "id": "51423",
                    "votes": 57938
                },
                {
                    "id": "71716",
                    "votes": 87152
                }
            ],
            "progress": {
                "mode": "eevp",
                "pct": 0.8
            }
        },
        {
            "id": "51051",
            "results": [
                {
                    "id": "51423",
                    "votes": 17367
                },
                {
                    "id": "71716",
                    "votes": 14586
                }
            ],
            "progress": {
                "mode": "eevp",
                "pct": 0.49
            }
        },
        {
            "id": "51053",
            "results": [
                {
                    "id": "51423",
                    "votes": 30652
                },
                {
                    "id": "71716",
                    "votes": 85291
                }
            ],
            "progress": {
                "mode": "eevp",
                "pct": 0.5
            }
        },
        {
            "id": "51057",
            "results": [
                {
                    "id": "51423",
                    "votes": 78323
                },
                {
                    "id": "71716",
                    "votes": 21825
                }
            ],
            "progress": {
                "mode": "eevp",
                "pct": 0.67
            }
        },
        {
            "id": "51059",
            "results": [
                {
                    "id": "51423",
                    "votes": 77481
                },
                {
                    "id": "71716",
                    "votes": 53180
                }
            ],
            "progress": {
                "mode": "eevp",
                "pct": 0.92
            }
        },
        {
            "id": "51061",
            "results": [
                {
                    "id": "51423",
                    "votes": 62874
                },
                {
                    "id": "71716",
                    "votes": 22435
                }
            ],
            "progress": {
                "mode": "eevp",
                "pct": 0.36
            }
        },
        {
            "id": "51063",
            "results": [
                {
                    "id": "51423",
                    "votes": 38008
                },
                {
                    "id": "71716",
                    "votes": 93737
                }
            ],
            "progress": {
                "mode": "eevp",
                "pct": 0.92
            }
        },
        {
            "id": "51065",
            "results": [
                {
                    "id": "51423",
                    "votes": 38341
                },
                {
                    "id": "71716",
                    "votes": 50964
                }
            ],
            "progress": {
                "mode": "eevp",
                "pct": 1.0
            }
        },
        {
            "id": "51067",
            "results": [
                {
                    "id": "51423",
                    "votes": 45968
                },
                {
                    "id": "71716",
                    "votes": 75348
                }
            ],
            "progress": {
                "mode": "eevp",
                "pct": 0.18
            }
        },
        {
            "id": "51069",
            "results": [
                {
                    "id": "51423",
                    "votes": 91430
                },
                {
                    "id": "71716",
                    "votes": 22605
                }
            ],
            "progress": {
                "mode": "eevp",
                "pct": 0.2
            }
        },
        {
            "id": "51071",
            "results": [
                {
                    "id": "51423",
                    "votes": 82530
                },
                {
                    "id": "71716",
                    "votes": 31172
                }
            ],
            "progress": {
                "mode": "eevp",
                "pct": 0.59
            }
        },
        {
            "id": "51073",
            "results": [
                {
                    "id": "51423",
                    "votes": 42795
                },
                {
                    "id": "71716",
                    "votes": 92578
                }
            ],
            "progress": {
                "mode": "eevp",
                "pct": 0.34
            }
        },
        {
            "id": "51075",
            "results": [
                {
                    "id": "51423",
                    "votes": 89546
                },
                {
                    "id": "71716",
                    "votes": 76562
                }
            ],
            "progress": {
                "mode": "eevp",
                "pct": 0.14
            }
        },
        {
            "id": "51077",
            "results": [
                {
                    "id": "51423",
                    "votes": 55566
                },
                {
                    "id": "71716",
                    "votes": 91056
                }
            ],
            "progress": {
                "mode": "eevp",
                "pct": 0.31
            }
        },
        {
            "id": "51079",
            "results": [
                {
                    "id": "51423",
                    "votes": 60090
                },
                {
                    "id": "71716",
                    "votes": 27951
                }
            ],
            "progress": {
                "mode": "eevp",
                "pct": 0.27
            }
        },
        {
            "id": "51081",
            "results": [
                {
                    "id": "51423",
                    "votes": 60007
                },
                {
                    "id": "71716",
                    "votes": 92080
                }
            ],
            "progress": {
                "mode": "eevp",
                "pct": 1.0
            }
        },
        {
            "id": "51083",
            "results": [
                {
                    "id": "51423",
                    "votes": 87442
                },
                {
                    "id": "71716",
                    "votes": 21317
                }
            ],
            "progress": {
                "mode": "eevp",
                "pct": 0.29
            }
        },
        {
            "id": "51085",
            "results": [
                {
                    "id": "51423",
                    "votes": 35077
                },
                {
                    "id": "71716",
                    "votes": 88164
                }
            ],
            "progress": {
                "mode": "eevp",
                "pct": 1.0
            }
        },
        {
            "id": "51087",
            "results": [
                {
                    "id": "51423",
                    "votes": 84139
                },
                {
                    "id": "71716",
                    "votes": 90174
                }
            ],
            "progress": {
                "mode": "eevp",
                "pct": 0.91
            }
        },
        {
            "id": "51089",
            "results": [
                {
                    "id": "51423",
                    "votes": 66067
                },
                {
                    "id": "71716",
                    "votes": 79365
                }
            ],
            "progress": {
                "mode": "eevp",
                "pct": 0.7
            }
        },
        {
            "id": "51091",
            "results": [
                {
                    "id": "51423",
                    "votes": 57258
                },
                {
                    "id": "71716",
                    "votes": 82714
                }
            ],
            "progress": {
                "mode": "eevp",
                "pct": 0.44
            }
        },
        {
            "id": "51093",
            "results": [
                {
                    "id": "51423",
                    "votes": 27169
                },
                {
                    "id": "71716",
                    "votes": 60588
                }
            ],
            "progress": {
                "mode": "eevp",
                "pct": 0.07
            }
        },
        {
            "id": "51095",
            "results": [
                {
                    "id": "51423",
                    "votes": 27849
                },
                {
                    "id": "71716",
                    "votes": 95118
                }
            ],
            "progress": {
                "mode": "eevp",
                "pct": 0.64
            }
        },
        {
            "id": "51097",
            "results": [
                {
                    "id": "51423",
                    "votes": 11261
                },
                {
                    "id": "71716",
                    "votes": 34880
                }
            ],
            "progress": {
                "mode": "eevp",
                "pct": 0.19
            }
        },
        {
            "id": "51099",
            "results": [
                {
                    "id": "51423",
                    "votes": 57049
                },
                {
                    "id": "71716",
                    "votes": 90091
                }
            ],
            "progress": {
                "mode": "eevp",
                "pct": 0.41
            }
        },
        {
            "id": "51101",
            "results": [
                {
                    "id": "51423",
                    "votes": 88331
                },
                {
                    "id": "71716",
                    "votes": 48837
                }
            ],
            "progress": {
                "mode": "eevp",
                "pct": 0.08
            }
        },
        {
            "id": "51103",
            "results": [
                {
                    "id": "51423",
                    "votes": 87371
                },
                {
                    "id": "71716",
                    "votes": 39105
                }
            ],
            "progress": {
                "mode": "eevp",
                "pct": 0.79
            }
        },
        {
            "id": "51105",
            "results": [
                {
                    "id": "51423",
                    "votes": 86574
                },
                {
                    "id": "71716",
                    "votes": 34004
                }
            ],
            "progress": {
                "mode": "eevp",
                "pct": 0.58
            }
        },
        {
            "id": "51107",
            "results": [
                {
                    "id": "51423",
                    "votes": 30251
                },
                {
                    "id": "71716",
                    "votes": 94698
                }
            ],
            "progress": {
                "mode": "eevp",
                "pct": 0.19
            }
        },
        {
            "id": "51109",
            "results": [
                {
                    "id": "51423",
                    "votes": 20859
                },
                {
                    "id": "71716",
                    "votes": 83686
                }
            ],
            "progress": {
                "mode": "eevp",
                "pct": 0.95
            }
        },
        {
            "id": "51111",
            "results": [
                {
                    "id": "51423",
                    "votes": 30049
                },
                {
                    "id": "71716",
                    "votes": 30058
                }
            ],
            "progress": {
                "mode": "eevp",
                "pct": 0.11
            }
        },
        {
            "id": "51113",
            "results": [
                {
                    "id": "51423",
                    "votes": 41844
                },
                {
                    "id": "71716",
                    "votes": 48289
                }
            ],
            "progress": {
                "mode": "eevp",
                "pct": 0.57
            }
        },
        {
            "id": "51115",
            "results": [
                {
                    "id": "51423",
                    "votes": 35370
                },
                {
                    "id": "71716",
                    "votes": 89902
                }
            ],
            "progress": {
                "mode": "eevp",
                "pct": 0.0
            }
        },
        {
            "id": "51117",
            "results": [
                {
                    "id": "51423",
                    "votes": 91110
                },
                {
                    "id": "71716",
                    "votes": 45654
                }
            ],
            "progress": {
                "mode": "eevp",
                "pct": 0.62
            }
        },
        {
            "id": "51119",
            "results": [
                {
                    "id": "51423",
                    "votes": 31366
                },
                {
                    "id": "71716",
                    "votes": 76763
                }
            ],
            "progress": {
                "mode": "eevp",
                "pct": 0.41
            }
        },
        {
            "id": "51121",
            "results": [
                {
                    "id": "51423",
                    "votes": 10856
                },
                {
                    "id": "71716",
                    "votes": 50632
                }
            ],
            "progress": {
                "mode": "eevp",
                "pct": 0.77
            }
        },
        {
            "id": "51125",
            "results": [
                {
                    "id": "51423",
                    "votes": 88260
                },
                {
                    "id": "71716",
                    "votes": 72832
                }
            ],
            "progress": {
                "mode": "eevp",
                "pct": 0.65
            }
        },
        {
            "id": "51127",
            "results": [
                {
                    "id": "51423",
                    "votes": 66698
                },
                {
                    "id": "71716",
                    "votes": 85371
                }
            ],
            "progress": {
                "mode": "eevp",
                "pct": 0.8
            }
        },
        {
            "id": "51131",
            "results": [
                {
                    "id": "51423",
                    "votes": 98466
                },
                {
                    "id": "71716",
                    "votes": 25724
                }
            ],
            "progress": {
                "mode": "eevp",
                "pct": 0.24
            }
        },
        {
            "id": "51133",
            "results": [
                {
                    "id": "51423",
                    "votes": 11148
                },
                {
                    "id": "71716",
                    "votes": 63126
                }
            ],
            "progress": {
                "mode": "eevp",
                "pct": 0.24
            }
        },
        {
            "id": "51135",
            "results": [
                {
                    "id": "51423",
                    "votes": 94202
                },
                {
                    "id": "71716",
                    "votes": 57515
                }
            ],
            "progress": {
                "mode": "eevp",
                "pct": 0.51
            }
        },
        {
            "id": "51137",
            "results": [
                {
                    "id": "51423",
                    "votes": 64078
                },
                {
                    "id": "71716",
                    "votes": 51765
                }
            ],
            "progress": {
                "mode": "eevp",
                "pct": 0.55
            }
        },
        {
            "id": "51139",
            "results": [
                {
                    "id": "51423",
                    "votes": 40077
                },
                {
                    "id": "71716",
                    "votes": 13147
                }
            ],
            "progress": {
                "mode": "eevp",
                "pct": 0.64
            }
        },
        {
            "id": "51141",
            "results": [
                {
                    "id": "51423",
                    "votes": 45823
                },
                {
                    "id": "71716",
                    "votes": 72775
                }
            ],
            "progress": {
                "mode": "eevp",
                "pct": 0.95
            }
        },
        {
            "id": "51143",
            "results": [
                {
                    "id": "51423",
                    "votes": 80232
                },
                {
                    "id": "71716",
                    "votes": 51996
                }
            ],
            "progress": {
                "mode": "eevp",
                "pct": 0.58
            }
        },
        {
            "id": "51145",
            "results": [
                {
                    "id": "51423",
                    "votes": 25119
                },
                {
                    "id": "71716",
                    "votes": 34071
                }
            ],
            "progress": {
                "mode": "eevp",
                "pct": 0.55
            }
        },
        {
            "id": "51147",
            "results": [
                {
                    "id": "51423",
                    "votes": 73101
                },
                {
                    "id": "71716",
                    "votes": 16021
                }
            ],
            "progress": {
                "mode": "eevp",
                "pct": 0.44
            }
        },
        {
            "id": "51149",
            "results": [
                {
                    "id": "51423",
                    "votes": 76213
                },
                {
                    "id": "71716",
                    "votes": 55145
                }
            ],
            "progress": {
                "mode": "eevp",
                "pct": 0.75
            }
        },
        {
            "id": "51153",
            "results": [
                {
                    "id": "51423",
                    "votes": 37075
                },
                {
                    "id": "71716",
                    "votes": 66629
                }
            ],
            "progress": {
                "mode": "eevp",
                "pct": 0.36
            }
        },
        {
            "id": "51155",
            "results": [
                {
                    "id": "51423",
                    "votes": 76459
                },
                {
                    "id": "71716",
                    "votes": 80097
                }
            ],
            "progress": {
                "mode": "eevp",
                "pct": 0.85
            }
        },
        {
            "id": "51157",
            "results": [
                {
                    "id": "51423",
                    "votes": 76893
                },
                {
                    "id": "71716",
                    "votes": 52814
                }
            ],
            "progress": {
                "mode": "eevp",
                "pct": 0.42
            }
        },
        {
            "id": "51159",
            "results": [
                {
                    "id": "51423",
                    "votes": 58344
                },
                {
                    "id": "71716",
                    "votes": 25095
                }
            ],
            "progress": {
                "mode": "eevp",
                "pct": 0.87
            }
        },
        {
            "id": "51161",
            "results": [
                {
                    "id": "51423",
                    "votes": 69857
                },
                {
                    "id": "71716",
                    "votes": 15620
                }
            ],
            "progress": {
                "mode": "eevp",
                "pct": 0.8
            }
        },
        {
            "id": "51163",
            "results": [
                {
                    "id": "51423",
                    "votes": 24700
                },
                {
                    "id": "71716",
                    "votes": 43720
                }
            ],
            "progress": {
                "mode": "eevp",
                "pct": 0.94
            }
        },
        {
            "id": "51165",
            "results": [
                {
                    "id": "51423",
                    "votes": 70689
                },
                {
                    "id": "71716",
                    "votes": 83235
                }
            ],
            "progress": {
                "mode": "eevp",
                "pct": 0.8
            }
        },
        {
            "id": "51167",
            "results": [
                {
                    "id": "51423",
                    "votes": 33247
                },
                {
                    "id": "71716",
                    "votes": 68322
                }
            ],
            "progress": {
                "mode": "eevp",
                "pct": 0.74
            }
        },
        {
            "id": "51169",
            "results": [
                {
                    "id": "51423",
                    "votes": 34739
                },
                {
                    "id": "71716",
                    "votes": 90192
                }
            ],
            "progress": {
                "mode": "eevp",
                "pct": 0.19
            }
        },
        {
            "id": "51171",
            "results": [
                {
                    "id": "51423",
                    "votes": 61343
                },
                {
                    "id": "71716",
                    "votes": 18262
                }
            ],
            "progress": {
                "mode": "eevp",
                "pct": 0.49
            }
        },
        {
            "id": "51173",
            "results": [
                {
                    "id": "51423",
                    "votes": 64538
                },
                {
                    "id": "71716",
                    "votes": 19854
                }
            ],
            "progress": {
                "mode": "eevp",
                "pct": 0.1
            }
        },
        {
            "id": "51175",
            "results": [
                {
                    "id": "51423",
                    "votes": 96115
                },
                {
                    "id": "71716",
                    "votes": 24619
                }
            ],
            "progress": {
                "mode": "eevp",
                "pct": 0.93
            }
        },
        {
            "id": "51177",
            "results": [
                {
                    "id": "51423",
                    "votes": 19625
                },
                {
                    "id": "71716",
                    "votes": 18258
                }
            ],
            "progress": {
                "mode": "eevp",
                "pct": 0.73
            }
        },
        {
            "id": "51179",
            "results": [
                {
                    "id": "51423",
                    "votes": 43800
                },
                {
                    "id": "71716",
                    "votes": 55254
                }
            ],
            "progress": {
                "mode": "eevp",
                "pct": 0.46
            }
        },
        {
            "id": "51181",
            "results": [
                {
                    "id": "51423",
                    "votes": 36268
                },
                {
                    "id": "71716",
                    "votes": 54927
                }
            ],
            "progress": {
                "mode": "eevp",
                "pct": 0.85
            }
        },
        {
            "id": "51183",
            "results": [
                {
                    "id": "51423",
                    "votes": 89249
                },
                {
                    "id": "71716",
                    "votes": 34432
                }
            ],
            "progress": {
                "mode": "eevp",
                "pct": 0.3
            }
        },
        {
            "id": "51185",
            "results": [
                {
                    "id": "51423",
                    "votes": 61138
                },
                {
                    "id": "71716",
                    "votes": 76817
                }
            ],
            "progress": {
                "mode": "eevp",
                "pct": 0.88
            }
        },
        {
            "id": "51187",
            "results": [
                {
                    "id": "51423",
                    "votes": 99271
                },
                {
                    "id": "71716",
                    "votes": 99902
                }
            ],
            "progress": {
                "mode": "eevp",
                "pct": 0.7
            }
        },
        {
            "id": "51191",
            "results": [
                {
                    "id": "51423",
                    "votes": 17070
                },
                {
                    "id": "71716",
                    "votes": 95416
                }
            ],
            "progress": {
                "mode": "eevp",
                "pct": 0.58
            }
        },
        {
            "id": "51193",
            "results": [
                {
                    "id": "51423",
                    "votes": 20686
                },
                {
                    "id": "71716",
                    "votes": 78830
                }
            ],
            "progress": {
                "mode": "eevp",
                "pct": 0.47
            }
        },
        {
            "id": "51195",
            "results": [
                {
                    "id": "51423",
                    "votes": 81001
                },
                {
                    "id": "71716",
                    "votes": 45161
                }
            ],
            "progress": {
                "mode": "eevp",
                "pct": 0.27
            }
        },
        {
            "id": "51197",
            "results": [
                {
                    "id": "51423",
                    "votes": 15806
                },
                {
                    "id": "71716",
                    "votes": 30305
                }
            ],
            "progress": {
                "mode": "eevp",
                "pct": 0.8
            }
        },
        {
            "id": "51199",
            "results": [
                {
                    "id": "51423",
                    "votes": 43634
                },
                {
                    "id": "71716",
                    "votes": 30746
                }
            ],
            "progress": {
                "mode": "eevp",
                "pct": 0.7
            }
        },
        {
            "id": "51510",
            "results": [
                {
                    "id": "51423",
                    "votes": 86625
                },
                {
                    "id": "71716",
                    "votes": 99639
                }
            ],
            "progress": {
                "mode": "eevp",
                "pct": 0.64
            }
        },
        {
            "id": "51520",
            "results": [
                {
                    "id": "51423",
                    "votes": 46572
                },
                {
                    "id": "71716",
                    "votes": 94038
                }
            ],
            "progress": {
                "mode": "eevp",
                "pct": 0.39
            }
        },
        {
            "id": "51530",
            "results": [
                {
                    "id": "51423",
                    "votes": 42694
                },
                {
                    "id": "71716",
                    "votes": 30459
                }
            ],
            "progress": {
                "mode": "eevp",
                "pct": 0.54
            }
        },
        {
            "id": "51540",
            "results": [
                {
                    "id": "51423",
                    "votes": 48817
                },
                {
                    "id": "71716",
                    "votes": 83787
                }
            ],
            "progress": {
                "mode": "eevp",
                "pct": 0.63
            }
        },
        {
            "id": "51550",
            "results": [
                {
                    "id": "51423",
                    "votes": 51421
                },
                {
                    "id": "71716",
                    "votes": 79377
                }
            ],
            "progress": {
                "mode": "eevp",
                "pct": 0.95
            }
        },
        {
            "id": "51570",
            "results": [
                {
                    "id": "51423",
                    "votes": 80922
                },
                {
                    "id": "71716",
                    "votes": 78992
                }
            ],
            "progress": {
                "mode": "eevp",
                "pct": 0.23
            }
        },
        {
            "id": "51580",
            "results": [
                {
                    "id": "51423",
                    "votes": 27712
                },
                {
                    "id": "71716",
                    "votes": 81297
                }
            ],
            "progress": {
                "mode": "eevp",
                "pct": 0.28
            }
        },
        {
            "id": "51590",
            "results": [
                {
                    "id": "51423",
                    "votes": 28450
                },
                {
                    "id": "71716",
                    "votes": 34822
                }
            ],
            "progress": {
                "mode": "eevp",
                "pct": 0.35
            }
        },
        {
            "id": "51595",
            "results": [
                {
                    "id": "51423",
                    "votes": 36055
                },
                {
                    "id": "71716",
                    "votes": 21094
                }
            ],
            "progress": {
                "mode": "eevp",
                "pct": 0.97
            }
        },
        {
            "id": "51600",
            "results": [
                {
                    "id": "51423",
                    "votes": 78618
                },
                {
                    "id": "71716",
                    "votes": 65940
                }
            ],
            "progress": {
                "mode": "eevp",
                "pct": 0.79
            }
        },
        {
            "id": "51610",
            "results": [
                {
                    "id": "51423",
                    "votes": 95271
                },
                {
                    "id": "71716",
                    "votes": 45922
                }
            ],
            "progress": {
                "mode": "eevp",
                "pct": 0.86
            }
        },
        {
            "id": "51620",
            "results": [
                {
                    "id": "51423",
                    "votes": 82509
                },
                {
                    "id": "71716",
                    "votes": 19524
                }
            ],
            "progress": {
                "mode": "eevp",
                "pct": 0.48
            }
        },
        {
            "id": "51630",
            "results": [
                {
                    "id": "51423",
                    "votes": 49591
                },
                {
                    "id": "71716",
                    "votes": 69731
                }
            ],
            "progress": {
                "mode": "eevp",
                "pct": 0.47
            }
        },
        {
            "id": "51640",
            "results": [
                {
                    "id": "51423",
                    "votes": 28889
                },
                {
                    "id": "71716",
                    "votes": 86047
                }
            ],
            "progress": {
                "mode": "eevp",
                "pct": 0.78
            }
        },
        {
            "id": "51650",
            "results": [
                {
                    "id": "51423",
                    "votes": 10257
                },
                {
                    "id": "71716",
                    "votes": 61512
                }
            ],
            "progress": {
                "mode": "eevp",
                "pct": 0.09
            }
        },
        {
            "id": "51660",
            "results": [
                {
                    "id": "51423",
                    "votes": 70393
                },
                {
                    "id": "71716",
                    "votes": 89094
                }
            ],
            "progress": {
                "mode": "eevp",
                "pct": 0.32
            }
        },
        {
            "id": "51670",
            "results": [
                {
                    "id": "51423",
                    "votes": 64624
                },
                {
                    "id": "71716",
                    "votes": 49197
                }
            ],
            "progress": {
                "mode": "eevp",
                "pct": 1.0
            }
        },
        {
            "id": "51678",
            "results": [
                {
                    "id": "51423",
                    "votes": 61804
                },
                {
                    "id": "71716",
                    "votes": 88049
                }
            ],
            "progress": {
                "mode": "eevp",
                "pct": 0.98
            }
        },
        {
            "id": "51680",
            "results": [
                {
                    "id": "51423",
                    "votes": 45772
                },
                {
                    "id": "71716",
                    "votes": 96456
                }
            ],
            "progress": {
                "mode": "eevp",
                "pct": 0.56
            }
        },
        {
            "id": "51683",
            "results": [
                {
                    "id": "51423",
                    "votes": 49439
                },
                {
                    "id": "71716",
                    "votes": 42301
                }
            ],
            "progress": {
                "mode": "eevp",
                "pct": 0.1
            }
        },
        {
            "id": "51685",
            "results": [
                {
                    "id": "51423",
                    "votes": 90474
                },
                {
                    "id": "71716",
                    "votes": 35110
                }
            ],
            "progress": {
                "mode": "eevp",
                "pct": 0.54
            }
        },
        {
            "id": "51690",
            "results": [
                {
                    "id": "51423",
                    "votes": 40409
                },
                {
                    "id": "71716",
                    "votes": 18780
                }
            ],
            "progress": {
                "mode": "eevp",
                "pct": 0.99
            }
        },
        {
            "id": "51700",
            "results": [
                {
                    "id": "51423",
                    "votes": 41197
                },
                {
                    "id": "71716",
                    "votes": 63877
                }
            ],
            "progress": {
                "mode": "eevp",
                "pct": 0.38
            }
        },
        {
            "id": "51710",
            "results": [
                {
                    "id": "51423",
                    "votes": 35526
                },
                {
                    "id": "71716",
                    "votes": 23100
                }
            ],
            "progress": {
                "mode": "eevp",
                "pct": 0.86
            }
        },
        {
            "id": "51720",
            "results": [
                {
                    "id": "51423",
                    "votes": 92539
                },
                {
                    "id": "71716",
                    "votes": 78140
                }
            ],
            "progress": {
                "mode": "eevp",
                "pct": 0.63
            }
        },
        {
            "id": "51730",
            "results": [
                {
                    "id": "51423",
                    "votes": 78822
                },
                {
                    "id": "71716",
                    "votes": 22423
                }
            ],
            "progress": {
                "mode": "eevp",
                "pct": 0.18
            }
        },
        {
            "id": "51735",
            "results": [
                {
                    "id": "51423",
                    "votes": 64933
                },
                {
                    "id": "71716",
                    "votes": 30455
                }
            ],
            "progress": {
                "mode": "eevp",
                "pct": 0.35
            }
        },
        {
            "id": "51740",
            "results": [
                {
                    "id": "51423",
                    "votes": 79400
                },
                {
                    "id": "71716",
                    "votes": 69184
                }
            ],
            "progress": {
                "mode": "eevp",
                "pct": 0.24
            }
        },
        {
            "id": "51750",
            "results": [
                {
                    "id": "51423",
                    "votes": 36469
                },
                {
                    "id": "71716",
                    "votes": 13420
                }
            ],
            "progress": {
                "mode": "eevp",
                "pct": 0.83
            }
        },
        {
            "id": "51760",
            "results": [
                {
                    "id": "51423",
                    "votes": 44934
                },
                {
                    "id": "71716",
                    "votes": 28335
                }
            ],
            "progress": {
                "mode": "eevp",
                "pct": 0.99
            }
        },
        {
            "id": "51770",
            "results": [
                {
                    "id": "51423",
                    "votes": 59163
                },
                {
                    "id": "71716",
                    "votes": 10537
                }
            ],
            "progress": {
                "mode": "eevp",
                "pct": 0.04
            }
        },
        {
            "id": "51775",
            "results": [
                {
                    "id": "51423",
                    "votes": 45693
                },
                {
                    "id": "71716",
                    "votes": 54813
                }
            ],
            "progress": {
                "mode": "eevp",
                "pct": 1.0
            }
        },
        {
            "id": "51790",
            "results": [
                {
                    "id": "51423",
                    "votes": 50079
                },
                {
                    "id": "71716",
                    "votes": 65490
                }
            ],
            "progress": {
                "mode": "eevp",
                "pct": 0.99
            }
        },
        {
            "id": "51800",
            "results": [
                {
                    "id": "51423",
                    "votes": 35166
                },
                {
                    "id": "71716",
                    "votes": 17464
                }
            ],
            "progress": {
                "mode": "eevp",
                "pct": 0.37
            }
        },
        {
            "id": "51810",
            "results": [
                {
                    "id": "51423",
                    "votes": 50489
                },
                {
                    "id": "71716",
                    "votes": 10055
                }
            ],
            "progress": {
                "mode": "eevp",
                "pct": 0.9
            }
        },
        {
            "id": "51820",
            "results": [
                {
                    "id": "51423",
                    "votes": 49823
                },
                {
                    "id": "71716",
                    "votes": 71687
                }
            ],
            "progress": {
                "mode": "eevp",
                "pct": 0.3
            }
        },
        {
            "id": "51830",
            "results": [
                {
                    "id": "51423",
                    "votes": 64214
                },
                {
                    "id": "71716",
                    "votes": 14547
                }
            ],
            "progress": {
                "mode": "eevp",
                "pct": 0.77
            }
        },
        {
            "id": "51840",
            "results": [
                {
                    "id": "51423",
                    "votes": 51226
                },
                {
                    "id": "71716",
                    "votes": 20342
                }
            ],
            "progress": {
                "mode": "eevp",
                "pct": 0.38
            }
        }
    ]
}