{
    "eventId": "2024-11-05",
    "id": "2024-11-05-collection-governor",
    "contests": [
        {
            "eventId": "2024-11-05",
            "resultsType": "live",
            "id": "ap:10:8080",
            "timestamp": "2024-09-28T02:48:49.832000Z",
            "results": [
                {
                    "votes": 178305,
                    "id": "10289"
                },
                {
                    "votes": 193269,
                    "id": "103922"
                }
            ],
            "progress": {
                "mode": "eevp",
                "pct": 0.31
            },
            "status": {
                "tabulation": "before",
                "recount": "none"
            },
            "calls": []
        },
        {
            "eventId": "2024-11-05",
            "resultsType": "live",
            "id": "ap:18:15007",
            "timestamp": "2024-09-25T14:34:04.346000Z",
            "results": [
                {
                    "votes": 5353265,
                    "id": "162889"
                },
                {
                    "votes": 4974922,
                    "id": "66197"
                },
                {
                    "votes": 49090,
                    "id": "69533"
                }
            ],
            "progress": {
                "mode": "eevp",
                "pct": 0.12
            },
            "status": {
                "tabulation": "before",
                "recount": "none"
            },
            "calls": []
        },
        {
            "eventId": "2024-11-05",
            "resultsType": "live",
            "id": "ap:29:26795",
            "timestamp": "2024-09-25T14:34:23.361000Z",
            "results": [
                {
                    "votes": 6663821,
                    "id": "130548"
                },
                {
                    "votes": 6709680,
                    "id": "131139"
                },
                {
                    "votes": 62985,
                    "id": "131746"
                },
                {
                    "votes": 65411,
                    "id": "62422"
                }
            ],
            "progress": {
                "mode": "eevp",
                "pct": 0.11
            },
            "status": {
                "tabulation": "before",
                "recount": "none"
            },
            "calls": []
        },
        {
            "eventId": "2024-11-05",
            "resultsType": "live",
            "id": "ap:30:27003",
            "timestamp": "2024-09-25T14:33:36.924000Z",
            "results": [
                {
                    "votes": 3188751,
                    "id": "163469"
                },
                {
                    "votes": 3191044,
                    "id": "65131"
                },
                {
                    "votes": 31990,
                    "id": "167872"
                }
            ],
            "progress": {
                "mode": "eevp",
                "pct": 0.29
            },
            "status": {
                "tabulation": "before",
                "recount": "none"
            },
            "calls": []
        },
        {
            "eventId": "2024-11-05",
            "resultsType": "live",
            "id": "ap:37:35392",
            "timestamp": "2024-09-25T14:32:56.527000Z",
            "results": [
                {
                    "votes": 5359168,
                    "id": "134769"
                },
                {
                    "votes": 5819397,
                    "id": "136491"
                },
                {
                    "votes": 53560,
                    "id": "166374"
                },
                {
                    "votes": 54516,
                    "id": "166375"
                },
                {
                    "votes": 50678,
                    "id": "167551"
                }
            ],
            "progress": {
                "mode": "eevp",
                "pct": 0.48
            },
            "status": {
                "tabulation": "before",
                "recount": "none"
            },
            "calls": []
        },
        {
            "eventId": "2024-11-05",
            "resultsType": "live",
            "id": "ap:38:35343",
            "timestamp": "2024-09-25T14:33:51.691000Z",
            "results": [
                {
                    "votes": 3031223,
                    "id": "134943"
                },
                {
                    "votes": 3118607,
                    "id": "66922"
                },
                {
                    "votes": 30931,
                    "id": "68733"
                }
            ],
            "progress": {
                "mode": "eevp",
                "pct": 0.54
            },
            "status": {
                "tabulation": "before",
                "recount": "none"
            },
            "calls": []
        },
        {
            "eventId": "2024-11-05",
            "resultsType": "live",
            "id": "ap:33:30005",
            "timestamp": "2024-09-25T14:34:49.461000Z",
            "results": [
                {
                    "votes": 13600828,
                    "id": "165213"
                },
                {
                    "votes": 13227490,
                    "id": "61040"
                },
                {
                    "votes": 134315,
                    "id": "168217"
                }
            ],
            "progress": {
                "mode": "eevp",
                "pct": 0.81
            },
            "status": {
                "tabulation": "before",
                "recount": "none"
            },
            "calls": []
        },
        {
            "eventId": "2024-11-05",
            "resultsType": "live",
            "id": "ap:49:45672",
            "timestamp": "2024-09-25T14:33:42.327000Z",
            "results": [
                {
                    "votes": 1604530,
                    "id": "164467"
                },
                {
                    "votes": 16402,
                    "id": "44473"
                },
                {
                    "votes": 1720556,
                    "id": "68830"
                },
                {
                    "votes": 16558,
                    "id": "70420"
                },
                {
                    "votes": 15900,
                    "id": "167353"
                }
            ],
            "progress": {
                "mode": "eevp",
                "pct": 0.67
            },
            "status": {
                "tabulation": "before",
                "recount": "none"
            },
            "calls": []
        },
        {
            "eventId": "2024-11-05",
            "resultsType": "live",
            "id": "ap:50:46375",
            "timestamp": "2024-09-25T14:34:31.777000Z",
            "results": [
                {
                    "votes": 14245639,
                    "id": "164617"
                },
                {
                    "votes": 14180970,
                    "id": "45443"
                },
                {
                    "votes": 143018,
                    "id": "69498"
                },
                {
                    "votes": 138911,
                    "id": "167786"
                },
                {
                    "votes": 142113,
                    "id": "167782"
                }
            ],
            "progress": {
                "mode": "eevp",
                "pct": 0.26
            },
            "status": {
                "tabulation": "before",
                "recount": "none"
            },
            "calls": []
        },
        {
            "eventId": "2024-11-05",
            "resultsType": "live",
            "id": "ap:53:48022",
            "timestamp": "2024-09-25T14:34:18.942000Z",
            "results": [
                {
                    "votes": 1986055,
                    "id": "149729"
                },
                {
                    "votes": 1964548,
                    "id": "50215"
                }
            ],
            "progress": {
                "mode": "eevp",
                "pct": 0.44
            },
            "status": {
                "tabulation": "before",
                "recount": "none"
            },
            "calls": []
        },
        {
            "eventId": "2024-11-05",
            "resultsType": "live",
            "id": "ap:54:49136",
            "timestamp": "2024-09-28T02:50:17.990000Z",
            "results": [
                {
                    "votes": 31041,
                    "id": "155104"
                },
                {
                    "votes": 2873266,
                    "id": "162001"
                },
                {
                    "votes": 31139,
                    "id": "166876"
                },
                {
                    "votes": 2987624,
                    "id": "66287"
                },
                {
                    "votes": 32975,
                    "id": "69619"
                }
            ],
            "progress": {
                "mode": "eevp",
                "pct": 0.79
            },
            "status": {
                "tabulation": "before",
                "recount": "none"
            },
            "calls": []
        }
    ]
}